MANIFEST.in
README.md
requirements.txt
setup.py
app_page/__init__.py
app_page/app.py
app_page/apprcc_rc.py
app_page/config.py
app_page.egg-info/PKG-INFO
app_page.egg-info/SOURCES.txt
app_page.egg-info/dependency_links.txt
app_page.egg-info/not-zip-safe
app_page.egg-info/requires.txt
app_page.egg-info/top_level.txt
app_page/animation/FadeEffect.py
app_page/animation/Loading.py
app_page/animation/MoveWin.py
app_page/animation/RightClick.py
app_page/animation/ScrollMethod.py
app_page/animation/Shadow.py
app_page/animation/ShakeEffect.py
app_page/animation/__init__.py
app_page/assets/favicon.png
app_page/assets/loading.gif
app_page/assets/maximize_page.png
app_page/assets/skin_card.ui
app_page/assets/small_page.png
app_page/assets/tips.ui
app_page/assets/tipsBox.ui
app_page/assets/image/avatar.png
app_page/assets/menu/classify.png
app_page/assets/menu/delete.png
app_page/assets/menu/down-arrow.png
app_page/assets/menu/edit.png
app_page/assets/menu/label.png
app_page/assets/menu/love.png
app_page/assets/menu/mark.png
app_page/assets/menu/pictures.png
app_page/assets/menu/remove.png
app_page/assets/menu/search.png
app_page/assets/menu/setting.png
app_page/assets/menu/share.png
app_page/assets/menu/style.png
app_page/assets/menu/up-arrow.png
app_page/assets/menu/write.png
app_page/assets/skin/app_bg_image_1.png
app_page/assets/skin/app_bg_image_2.png
app_page/assets/skin/app_bg_image_3.png
app_page/components/Stack.py
app_page/components/StackManager.py
app_page/components/__init__.py
app_page/core/Device.py
app_page/core/EventBus.py
app_page/core/EventHook.py
app_page/core/FileParam.py
app_page/core/MainWindow.py
app_page/core/MoveEventMechine.py
app_page/core/Page.py
app_page/core/PageManager.py
app_page/core/Record.py
app_page/core/Setting.py
app_page/core/Thread.py
app_page/core/Tips.py
app_page/core/TipsBox.py
app_page/core/__init__.py
app_page/core/render.py
app_page/core/ui_main.py
app_page/example/Skin.py
app_page/example/__init__.py
app_page/plugins/Excel.py
app_page/plugins/MQTT.py
app_page/plugins/__init__.py
app_page/utils/__init__.py
app_page/utils/common.py
app_page/utils/cut_image.py
app_page/utils/load_ui.py
app_page/utils/select_image.py
