Metadata-Version: 2.1
Name: app-page
Version: 0.0.30
Summary: PySide6 page application framework
Home-page: https://github.com/xiaohuicat/python-app-page
Author: xiaohuicat
Author-email: 1258702350@qq.com
License: MIT
Requires-Dist: app-page-core>=0.0.6
Requires-Dist: nanoid
Requires-Dist: PySide6
Requires-Dist: pywin32
Requires-Dist: numpy
Requires-Dist: openpyxl
Requires-Dist: paho-mqtt==1.6.1
Requires-Dist: pillow
